mcp_powerpoint/__init__.py
mcp_powerpoint/__main__.py
mcp_powerpoint/powerpoint_models.py
mcp_powerpoint/powerpoint_server.py
mcp_powerpoint/shape_naming_server.py
mcp_powerpoint-1.0.0.dist-info/licenses/LICENSE
mcp_powerpoint-1.0.0.dist-info/METADATA
mcp_powerpoint-1.0.0.dist-info/WHEEL
mcp_powerpoint-1.0.0.dist-info/entry_points.txt
mcp_powerpoint-1.0.0.dist-info/top_level.txt
mcp_powerpoint-1.0.0.dist-info/RECORD
