Metadata-Version: 2.4
Name: mcp-powerpoint
Version: 1.0.0
Summary: MCP server for PowerPoint file manipulation and shape naming using Ollama LLM
Author: MCP PowerPoint Tools
License-Expression: MIT
Project-URL: Homepage, https://github.com/your-username/mcp-powerpoint
Project-URL: Repository, https://github.com/your-username/mcp-powerpoint.git
Project-URL: Issues, https://github.com/your-username/mcp-powerpoint/issues
Keywords: mcp,powerpoint,pptx,json,llm,ollama,shape-naming
Classifier: Development Status :: 4 - Beta
Classifier: Intended Audience :: Developers
Classifier: Programming Language :: Python :: 3
Classifier: Programming Language :: Python :: 3.12
Classifier: Topic :: Software Development :: Libraries :: Python Modules
Classifier: Topic :: Office/Business :: Office Suites
Classifier: Topic :: Text Processing :: Markup
Requires-Python: >=3.12
License-File: LICENSE
Requires-Dist: fastmcp>=2.12.2
Requires-Dist: ollama>=0.5.3
Requires-Dist: pillow>=11.3.0
Requires-Dist: pydantic>=2.11.7
Requires-Dist: python-pptx>=1.0.2
Requires-Dist: torch>=2.8.0
Requires-Dist: transformers>=4.56.1
Dynamic: license-file
